[
    {
        "command": "homeEndFactor",
        "timers": [
            {
                "duration": 0.034112002,
                "name": "Create Task Timer"
            },
            {
                "duration": 0.007074834,
                "name": "Initialize and Plan Task Timer"
            },
            {
                "duration": 2.148596317,
                "name": "Execute Task Timer"
            }
        ]
    },
    {
        "command": "moveToPoint:G2",
        "timers": [
            {
                "duration": 0.034184743,
                "name": "Create Task Timer"
            },
            {
                "duration": 0.007599075,
                "name": "Initialize and Plan Task Timer"
            },
            {
                "duration": 1.847519874,
                "name": "Execute Task Timer"
            }
        ]
    }
]